socials/__init__.py
socials/_version.py
socials/cli.py
socials/py.typed
socials/socials.py
socials-0.3.0.dist-info/METADATA
socials-0.3.0.dist-info/WHEEL
socials-0.3.0.dist-info/entry_points.txt
socials-0.3.0.dist-info/licenses/AUTHORS.md
socials-0.3.0.dist-info/licenses/LICENSE
socials-0.3.0.dist-info/RECORD
