Metadata-Version: 2.4
Name: socials
Version: 0.3.0
Summary: Social Account Detection for Python
Project-URL: Homepage, https://github.com/lorey/socials
Project-URL: Documentation, https://socials.readthedocs.io
Project-URL: Repository, https://github.com/lorey/socials
Project-URL: Changelog, https://github.com/lorey/socials/blob/main/CHANGELOG.md
Author-email: Karl Lorey <git@karllorey.com>
License-Expression: GPL-3.0-or-later
License-File: AUTHORS.md
License-File: LICENSE
Keywords: facebook,github,instagram,linkedin,social media,twitter,url extraction,youtube
Classifier: Development Status :: 4 - Beta
Classifier: Intended Audience :: Developers
Classifier: License :: OSI Approved :: GNU General Public License v3 (GPLv3)
Classifier: Natural Language :: English
Classifier: Programming Language :: Python :: 3
Classifier: Programming Language :: Python :: 3.9
Classifier: Programming Language :: Python :: 3.10
Classifier: Programming Language :: Python :: 3.11
Classifier: Programming Language :: Python :: 3.12
Classifier: Programming Language :: Python :: 3.13
Requires-Python: >=3.9
Requires-Dist: typer>=0.9
Provides-Extra: dev
Requires-Dist: mypy>=1.0; extra == 'dev'
Requires-Dist: pre-commit>=3.0; extra == 'dev'
Requires-Dist: pytest-cov>=4.0; extra == 'dev'
Requires-Dist: pytest>=8.0; extra == 'dev'
Requires-Dist: ruff>=0.8; extra == 'dev'
Provides-Extra: docs
Requires-Dist: mkdocs-material>=9.0; extra == 'docs'
Requires-Dist: mkdocs>=1.5; extra == 'docs'
